{
  "mainAssemblyName": "YachtLogHoursCalculator",
  "resources": {
    "hash": "sha256-SI8aXa9CWq85erm5H5nQAZta+5jQPnFQjHKt0stX+AM=",
    "fingerprinting": {
      "Microsoft.AspNetCore.Components.zvvi3fzkr9.wasm": "Microsoft.AspNetCore.Components.wasm",
      "Microsoft.AspNetCore.Components.Web.voypr8ybds.wasm": "Microsoft.AspNetCore.Components.Web.wasm",
      "Microsoft.AspNetCore.Components.WebAssembly.89ilifz4kl.wasm": "Microsoft.AspNetCore.Components.WebAssembly.wasm",
      "Microsoft.Extensions.Configuration.Abstractions.p3jduvb5cm.wasm": "Microsoft.Extensions.Configuration.Abstractions.wasm",
      "Microsoft.Extensions.Configuration.Json.080jiixfv5.wasm": "Microsoft.Extensions.Configuration.Json.wasm",
      "Microsoft.Extensions.Configuration.7qyoiz0n0f.wasm": "Microsoft.Extensions.Configuration.wasm",
      "Microsoft.Extensions.DependencyInjection.Abstractions.bqypj2vlj3.wasm": "Microsoft.Extensions.DependencyInjection.Abstractions.wasm",
      "Microsoft.Extensions.DependencyInjection.78esmno2al.wasm": "Microsoft.Extensions.DependencyInjection.wasm",
      "Microsoft.Extensions.Localization.Abstractions.amftx4vzy4.wasm": "Microsoft.Extensions.Localization.Abstractions.wasm",
      "Microsoft.Extensions.Localization.3h3z8cx0a3.wasm": "Microsoft.Extensions.Localization.wasm",
      "Microsoft.Extensions.Logging.Abstractions.35yfn2r18w.wasm": "Microsoft.Extensions.Logging.Abstractions.wasm",
      "Microsoft.Extensions.Logging.i4ete6t9pk.wasm": "Microsoft.Extensions.Logging.wasm",
      "Microsoft.Extensions.Options.35eso3yg95.wasm": "Microsoft.Extensions.Options.wasm",
      "Microsoft.Extensions.Primitives.pom9lwuay8.wasm": "Microsoft.Extensions.Primitives.wasm",
      "Microsoft.JSInterop.xh70ged7oa.wasm": "Microsoft.JSInterop.wasm",
      "Microsoft.JSInterop.WebAssembly.lsljofql11.wasm": "Microsoft.JSInterop.WebAssembly.wasm",
      "MudBlazor.x9cjshrb9i.wasm": "MudBlazor.wasm",
      "System.Collections.Concurrent.gcs2uvoo3f.wasm": "System.Collections.Concurrent.wasm",
      "System.Collections.Immutable.g2618qo6zd.wasm": "System.Collections.Immutable.wasm",
      "System.Collections.m46n96y7xi.wasm": "System.Collections.wasm",
      "System.ComponentModel.Primitives.nexkqknvz5.wasm": "System.ComponentModel.Primitives.wasm",
      "System.ComponentModel.m3ms7gmx60.wasm": "System.ComponentModel.wasm",
      "System.Console.w5mppkkpnv.wasm": "System.Console.wasm",
      "System.IO.Pipelines.z9mcxtggrr.wasm": "System.IO.Pipelines.wasm",
      "System.Linq.2kccic0n0y.wasm": "System.Linq.wasm",
      "System.Memory.h77ei90n6h.wasm": "System.Memory.wasm",
      "System.Net.Http.cvbabqwszi.wasm": "System.Net.Http.wasm",
      "System.Net.Primitives.avlxts81n2.wasm": "System.Net.Primitives.wasm",
      "System.Private.CoreLib.4w7il8mars.wasm": "System.Private.CoreLib.wasm",
      "System.Private.Uri.fscz7i5zqn.wasm": "System.Private.Uri.wasm",
      "System.Runtime.InteropServices.JavaScript.nf54u5jbpe.wasm": "System.Runtime.InteropServices.JavaScript.wasm",
      "System.Text.Encodings.Web.a9vs1egngd.wasm": "System.Text.Encodings.Web.wasm",
      "System.Text.Json.9oofkzdruv.wasm": "System.Text.Json.wasm",
      "System.Text.RegularExpressions.yqmu3do621.wasm": "System.Text.RegularExpressions.wasm",
      "YachtLogHoursCalculator.i7nfislxfn.wasm": "YachtLogHoursCalculator.wasm",
      "dotnet.native.qdz5v7zejv.js": "dotnet.native.js",
      "dotnet.native.vpzik8ghjq.wasm": "dotnet.native.wasm",
      "dotnet.js": "dotnet.js",
      "dotnet.runtime.cymp1amu5g.js": "dotnet.runtime.js"
    },
    "jsModuleNative": {
      "dotnet.native.qdz5v7zejv.js": "sha256-Xu3eksqA4LIgiLyRYVEZmBIIQryurGIr04w4DyQrfxA="
    },
    "jsModuleRuntime": {
      "dotnet.runtime.cymp1amu5g.js": "sha256-dCmS9Zx4egtLYSUgTI3R6gMS+Yg8MkzxW1CgEMJKAEw="
    },
    "wasmNative": {
      "dotnet.native.vpzik8ghjq.wasm": "sha256-rYauOC8CkVa2d5jNAVgIR8Rx5q1ewuBDmREDAqoexyw="
    },
    "coreAssembly": {
      "Microsoft.AspNetCore.Components.zvvi3fzkr9.wasm": "sha256-7yDF9ezYt8EqC4atlKez9hlQPapqt7VTX6FvwPTvw+Y=",
      "Microsoft.AspNetCore.Components.Web.voypr8ybds.wasm": "sha256-IYmaJkKcegKQ+nArJGN+s8T1yIJf4vQUhjZQI5abUH0=",
      "Microsoft.AspNetCore.Components.WebAssembly.89ilifz4kl.wasm": "sha256-VJIz0LcHgkeXpahkOWx6Q+C1ZDJ6O/GONFLzqZv+Jvw=",
      "Microsoft.Extensions.Configuration.Abstractions.p3jduvb5cm.wasm": "sha256-C7QKCociQofWMZXEilUdfndsOGsj6B93XYyYH3JyhZk=",
      "Microsoft.Extensions.Configuration.Json.080jiixfv5.wasm": "sha256-4DE0/WhaMaELUHzK5BQiiG9nOM0Z1qBgxqSSGRu8ESM=",
      "Microsoft.Extensions.Configuration.7qyoiz0n0f.wasm": "sha256-z0O30nECZ1Rk+PK4IacUyG14LoP7TkMPCroZXGfv5lw=",
      "Microsoft.Extensions.DependencyInjection.Abstractions.bqypj2vlj3.wasm": "sha256-7RgEEFLb0nibCPQfwVvm0JISVRLasInih5SPdnO02V8=",
      "Microsoft.Extensions.DependencyInjection.78esmno2al.wasm": "sha256-+TYftnpuawSVU4BKQRqWN+FwcPtVPqDHguupiwkWf0Y=",
      "Microsoft.Extensions.Localization.Abstractions.amftx4vzy4.wasm": "sha256-rgoLhQwsKSzO6Z3ObXGKIFvGXeaKjbXFl4y1+DTYDQk=",
      "Microsoft.Extensions.Localization.3h3z8cx0a3.wasm": "sha256-V8TcBTx7c+seF4BYVJGNXN1lG61hpq793aOVrfGfBIY=",
      "Microsoft.Extensions.Logging.Abstractions.35yfn2r18w.wasm": "sha256-lwlr7AOAI7xSdsqB7E4zBEPGPqchnyPHQE/y7H5Fe4o=",
      "Microsoft.Extensions.Logging.i4ete6t9pk.wasm": "sha256-Pl2WiwNj6e3gS79SBDqlxw9YpsuYy7WkMnAo/OD64ig=",
      "Microsoft.Extensions.Options.35eso3yg95.wasm": "sha256-aaVz57+rrhHdpwOZKe9+Ff8RHY1XeSWKRclucRFJzIY=",
      "Microsoft.Extensions.Primitives.pom9lwuay8.wasm": "sha256-5w9Gj2OjDfihspEQa6gox2H2a7h76WPN2ZF8DSAMAjg=",
      "Microsoft.JSInterop.xh70ged7oa.wasm": "sha256-C0Jp0xgF/TKMV7dxuo6B4zDjNHfPAZ634sbY9YiIVhs=",
      "Microsoft.JSInterop.WebAssembly.lsljofql11.wasm": "sha256-63bzxZLVvNOmTsso6iLrptxGmKBQh2HUIEGtPUrRPeQ=",
      "MudBlazor.x9cjshrb9i.wasm": "sha256-5bSkG5uTq0puZY06LPkIZKwSdrySoc7rD7GEWzEYRcE=",
      "System.Collections.Concurrent.gcs2uvoo3f.wasm": "sha256-ADZbsH5/nxwdBUFF2rQjqyIgyt/W2vstkVTQbHqYdIQ=",
      "System.Collections.Immutable.g2618qo6zd.wasm": "sha256-+ISI2FRwIAd70xCcOB+Gt6xoPmiNqTaysO2KqBpNK1c=",
      "System.Collections.m46n96y7xi.wasm": "sha256-xt8j+FjjoEUiS6UZ5gID0yqAhMmbj9255Tjl07AhN8I=",
      "System.ComponentModel.Primitives.nexkqknvz5.wasm": "sha256-H0DJaogKbkEjLUnlwpN7kPU5ENN+PALLOwnw65PHmVw=",
      "System.ComponentModel.m3ms7gmx60.wasm": "sha256-4qXZbapsDZssS5DvMcw49dIUrVfBIKsZ0zbsHsukBPQ=",
      "System.Console.w5mppkkpnv.wasm": "sha256-jLrjmH3+vqaMYpye29Uv2TfphSVKZwHQEiauJv/RYdI=",
      "System.IO.Pipelines.z9mcxtggrr.wasm": "sha256-Oa+YYnDz7Y7QdrHu4dSaDBejVaRUi9/iGQU2lLGJaPU=",
      "System.Linq.2kccic0n0y.wasm": "sha256-bnPqHpu2dhfEe4hAIpai0phiigRK4SbPEz0/WgjnyIE=",
      "System.Memory.h77ei90n6h.wasm": "sha256-Aw4naiS51l+EnNt5vDPiSZsX+R3cWlrIDbm4BxW8wA8=",
      "System.Net.Http.cvbabqwszi.wasm": "sha256-mO2B/+uXN7gzgyMidUcCJ3Mb51bQ+6rZ0OG5ofURUhs=",
      "System.Net.Primitives.avlxts81n2.wasm": "sha256-CibhF/tAsBSNw4oixhbAHkiVEhVm+U+OpcYR5MktQXU=",
      "System.Private.CoreLib.4w7il8mars.wasm": "sha256-jNLe/wsZQV+rrsw54UhRBkb37aOqau1N0ta+tp7JDPk=",
      "System.Private.Uri.fscz7i5zqn.wasm": "sha256-gdWPaOSPNs7IdstAt8aRQaVsjL1NX3N/3GvNxgbwOhw=",
      "System.Runtime.InteropServices.JavaScript.nf54u5jbpe.wasm": "sha256-g/aUkR3AQnsITw/gxxNj+qpKuLo5ESBNMANpklb/Yhk=",
      "System.Text.Encodings.Web.a9vs1egngd.wasm": "sha256-PuZffphL8LADAZQvfMteirU7MhnlkmuuGloIQj8NK+E=",
      "System.Text.Json.9oofkzdruv.wasm": "sha256-V0Uhdf/RmzrXh9D7tqjhWS2AGr5EzSWa8hO0MYkTx68=",
      "System.Text.RegularExpressions.yqmu3do621.wasm": "sha256-qgXCku4OPmJzo+SjieQuwR1bGkc/+v1L/rC/y8JRq6I=",
      "YachtLogHoursCalculator.i7nfislxfn.wasm": "sha256-PvUfBUM6RlkVRPgJC0JI+nfa99Kzk9TySvD52Cqof1A="
    },
    "assembly": {}
  },
  "cacheBootResources": true,
  "debugLevel": 0,
  "linkerEnabled": true,
  "globalizationMode": "invariant",
  "extensions": {
    "blazor": {}
  }
}